[
  {
    "full_name": "linuxserver/Heimdall",
    "stargazers_count": 5476,
    "open_issues_count": 18,
    "forks_count": 458
  },
  {
    "full_name": "linuxserver/docker-mods",
    "stargazers_count": 544,
    "open_issues_count": 56,
    "forks_count": 190
  },
  {
    "full_name": "im-n1/startpage",
    "stargazers_count": 5,
    "open_issues_count": 0,
    "forks_count": 0
  },
  {
    "full_name": "awesome-foss/awesome-sysadmin",
    "stargazers_count": 16491,
    "open_issues_count": 31,
    "forks_count": 1031
  },
  {
    "full_name": "lfzawacki/musical-artifacts",
    "stargazers_count": 88,
    "open_issues_count": 24,
    "forks_count": 6
  },
  {
    "full_name": "monicahq/monica",
    "stargazers_count": 18647,
    "open_issues_count": 584,
    "forks_count": 1839
  },
  {
    "full_name": "benphelps/homepage",
    "stargazers_count": 4078,
    "open_issues_count": 116,
    "forks_count": 224
  },
  {
    "full_name": "davestephens/ansible-nas",
    "stargazers_count": 2277,
    "open_issues_count": 110,
    "forks_count": 389
  },
  {
    "full_name": "awesome-selfhosted/awesome-selfhosted",
    "stargazers_count": 117366,
    "open_issues_count": 92,
    "forks_count": 6900
  },
  {
    "full_name": "opendatadiscovery/odd-platform",
    "stargazers_count": 691,
    "open_issues_count": 84,
    "forks_count": 37
  },
  {
    "full_name": "MartinKondor/MovieRecommender",
    "stargazers_count": 23,
    "open_issues_count": 1,
    "forks_count": 6
  },
  {
    "full_name": "jez500/bender",
    "stargazers_count": 76,
    "open_issues_count": 8,
    "forks_count": 2
  },
  {
    "full_name": "causefx/Organizr",
    "stargazers_count": 4207,
    "open_issues_count": 22,
    "forks_count": 277
  },
  {
    "full_name": "d4rk22/Network-Status-Page",
    "stargazers_count": 207,
    "open_issues_count": 1,
    "forks_count": 51
  },
  {
    "full_name": "aceberg/WatchYourLAN",
    "stargazers_count": 475,
    "open_issues_count": 14,
    "forks_count": 26
  },
  {
    "full_name": "rishavnandi/boiler_plates",
    "stargazers_count": 56,
    "open_issues_count": 0,
    "forks_count": 7
  },
  {
    "full_name": "orsinium-labs/generated-awesomeness",
    "stargazers_count": 263,
    "open_issues_count": 0,
    "forks_count": 44
  },
  {
    "full_name": "upscayl/upscayl",
    "stargazers_count": 9212,
    "open_issues_count": 35,
    "forks_count": 241
  },
  {
    "full_name": "ajnart/homarr",
    "stargazers_count": 1806,
    "open_issues_count": 48,
    "forks_count": 88
  },
  {
    "full_name": "veggiemonk/awesome-docker",
    "stargazers_count": 24238,
    "open_issues_count": 0,
    "forks_count": 2697
  },
  {
    "full_name": "yagmurerdogan/Doggy-App",
    "stargazers_count": 10,
    "open_issues_count": 0,
    "forks_count": 0
  },
  {
    "full_name": "dani-garcia/vaultwarden",
    "stargazers_count": 22593,
    "open_issues_count": 22,
    "forks_count": 1138
  },
  {
    "full_name": "Librum-Reader/Librum-Server",
    "stargazers_count": 30,
    "open_issues_count": 1,
    "forks_count": 0
  },
  {
    "full_name": "Librum-Reader/Librum",
    "stargazers_count": 183,
    "open_issues_count": 2,
    "forks_count": 3
  },
  {
    "full_name": "Leantime/docker-leantime",
    "stargazers_count": 88,
    "open_issues_count": 1,
    "forks_count": 47
  },
  {
    "full_name": "Leantime/leantime",
    "stargazers_count": 1996,
    "open_issues_count": 149,
    "forks_count": 360
  },
  {
    "full_name": "appsmithorg/appsmith",
    "stargazers_count": 24566,
    "open_issues_count": 3128,
    "forks_count": 2207
  },
  {
    "full_name": "itzg/docker-minecraft-server",
    "stargazers_count": 6078,
    "open_issues_count": 68,
    "forks_count": 1187
  },
  {
    "full_name": "j-delaney/easy-application",
    "stargazers_count": 7454,
    "open_issues_count": 42,
    "forks_count": 1012
  },
  {
    "full_name": "android/compose-samples",
    "stargazers_count": 14568,
    "open_issues_count": 17,
    "forks_count": 3496
  }
]